{"President": ["Alex Smith", "Jamie Johnson", "Taylor Brown"], "Vice President": ["Morgan Lee", "Casey Wilson", "Jordan Miller"], "Secretary": ["Riley Davis", "Quinn Thomas", "Avery Martin"], "Treasurer": ["Sam Roberts", "Drew Anderson", "Sydney Clark"], "Academic Officer": ["Charlie Robinson", "Skyler Adams", "Harper White"], "Social Chair": ["Dakota Green", "Reese Murphy", "Parker Young"], "Sports Representative": ["Jordan Hall", "Cameron Evans", "Taylor King"], "Media Officer": ["Alex James", "Morgan Hayes", "Riley Carter"]}